dataclass_io/__init__.py
dataclass_io/_lib/__init__.py
dataclass_io/_lib/assertions.py
dataclass_io/_lib/dataclass_extensions.py
dataclass_io/_lib/file.py
dataclass_io/reader.py
dataclass_io/writer.py
dataclass_io-0.2.0.dist-info/LICENSE
dataclass_io-0.2.0.dist-info/METADATA
dataclass_io-0.2.0.dist-info/WHEEL
dataclass_io-0.2.0.dist-info/RECORD
