Metadata-Version: 2.1
Name: dataclass_io
Version: 0.2.0
Summary: Dataclass IO
Home-page: https://github.com/msto/dataclass_io
Author: Matt Stone
Author-email: matt@fulcrumgenomics.com
Requires-Python: >=3.10,<4.0
Classifier: Development Status :: 3 - Alpha
Classifier: Programming Language :: Python :: 3
Classifier: Programming Language :: Python :: 3.10
Classifier: Programming Language :: Python :: 3.11
Classifier: Programming Language :: Python :: 3.12
Project-URL: Bug Tracker, https://github.com/msto/dataclass_io/issues
Project-URL: Documentation, https://github.com/msto/dataclass_io
Project-URL: Repository, https://github.com/msto/dataclass_io
